{"_type":"export","__export_format":4,"__export_date":"2020-01-12T17:21:12.001Z","__export_source":"insomnia.desktop.app:v7.0.6","resources":[{"_id":"req_b0b7c28ccc874ceeb3d08ef30d30d740","authentication":{"token":"{{ token  }}","type":"bearer"},"body":{},"created":1578842635099,"description":"","headers":[],"isPrivate":false,"metaSortKey":-1578842635099,"method":"GET","modified":1578842862003,"name":"List","parameters":[{"description":"","id":"pair_5f7b899b90e0451e9162fabc20c7482d","name":"date","value":"1578842851547"}],"parentId":"fld_28c6f6c8e2e64eb885d1699191be2b9b","settingDisableRenderRequestBody":false,"settingEncodeUrl":true,"settingFollowRedirects":"global","settingRebuildPath":true,"settingSendCookies":true,"settingStoreCookies":true,"url":"{{ base_url  }}/providers/1/available","_type":"request"},{"_id":"fld_28c6f6c8e2e64eb885d1699191be2b9b","created":1578842609701,"description":"","environment":{},"environmentPropertyOrder":null,"metaSortKey":-1578842609701,"modified":1578842609701,"name":"Available","parentId":"wrk_e5c94a721cc94e7e8b78ccd22896b9b0","_type":"request_group"},{"_id":"wrk_e5c94a721cc94e7e8b78ccd22896b9b0","created":1578674803541,"description":"","modified":1578674803541,"name":"Go Barber","parentId":null,"_type":"workspace"},{"_id":"req_b27216dc6c6443758f9b028e861a1a45","authentication":{"token":"{{ token  }}","type":"bearer"},"body":{},"created":1578783980904,"description":"","headers":[],"isPrivate":false,"metaSortKey":-1578783980904,"method":"GET","modified":1578784011615,"name":"List","parameters":[],"parentId":"fld_3c9d4a3026554d9bba106c30ff6b2ff7","settingDisableRenderRequestBody":false,"settingEncodeUrl":true,"settingFollowRedirects":"global","settingRebuildPath":true,"settingSendCookies":true,"settingStoreCookies":true,"url":"{{ base_url  }}/notifications","_type":"request"},{"_id":"fld_3c9d4a3026554d9bba106c30ff6b2ff7","created":1578783973158,"description":"","environment":{},"environmentPropertyOrder":null,"metaSortKey":-1578783973158,"modified":1578783973158,"name":"Notification","parentId":"wrk_e5c94a721cc94e7e8b78ccd22896b9b0","_type":"request_group"},{"_id":"req_4f97079157504b958522dc0bc0c20a84","authentication":{"token":"{{ token  }}","type":"bearer"},"body":{},"created":1578786079974,"description":"","headers":[],"isPrivate":false,"metaSortKey":-1578772903359.5,"method":"PUT","modified":1578786146266,"name":"Update","parameters":[],"parentId":"fld_3c9d4a3026554d9bba106c30ff6b2ff7","settingDisableRenderRequestBody":false,"settingEncodeUrl":true,"settingFollowRedirects":"global","settingRebuildPath":true,"settingSendCookies":true,"settingStoreCookies":true,"url":"{{ base_url  }}/notifications/5e1a573dae4acd41777932d9","_type":"request"},{"_id":"req_b27337ca17234284bd4442b8e21b0b68","authentication":{"token":"{{ token  }}","type":"bearer"},"body":{},"created":1578761825815,"description":"","headers":[],"isPrivate":false,"metaSortKey":-1578761825815,"method":"GET","modified":1578762430491,"name":"List","parameters":[{"description":"","id":"pair_26d37d2e87fb4078b4f56f6eccbb64fd","name":"date","value":"2020-01-11T00:00:00-03:00"}],"parentId":"fld_1dd45c6c36054c7092a6923098726fdd","settingDisableRenderRequestBody":false,"settingEncodeUrl":true,"settingFollowRedirects":"global","settingRebuildPath":true,"settingSendCookies":true,"settingStoreCookies":true,"url":"{{ base_url  }}/schedule","_type":"request"},{"_id":"fld_1dd45c6c36054c7092a6923098726fdd","created":1578761809207,"description":"","environment":{},"environmentPropertyOrder":null,"metaSortKey":-1578761809207,"modified":1578761809207,"name":"Schedule","parentId":"wrk_e5c94a721cc94e7e8b78ccd22896b9b0","_type":"request_group"},{"_id":"req_697edc59687b4282a5f9fc3d3a1dd6c6","authentication":{"token":"{{ token  }}","type":"bearer"},"body":{"mimeType":"application/json","text":"{\n\t\"provider_id\": 1,\n\t\"date\": \"2020-01-12T15:00:00-03:00\"\n\t\n}"},"created":1578757861286,"description":"","headers":[{"id":"pair_f4ca217813464a49a9f899cf348c3d7c","name":"Content-Type","value":"application/json"}],"isPrivate":false,"metaSortKey":-1578757861286,"method":"POST","modified":1578834195767,"name":"Create","parameters":[],"parentId":"fld_08cb52c5097640a78c444ca84a2f5637","settingDisableRenderRequestBody":false,"settingEncodeUrl":true,"settingFollowRedirects":"global","settingRebuildPath":true,"settingSendCookies":true,"settingStoreCookies":true,"url":"{{ base_url  }}/appointments","_type":"request"},{"_id":"fld_08cb52c5097640a78c444ca84a2f5637","created":1578757852828,"description":"","environment":{},"environmentPropertyOrder":null,"metaSortKey":-1578757852828,"modified":1578757852828,"name":"Appointments","parentId":"wrk_e5c94a721cc94e7e8b78ccd22896b9b0","_type":"request_group"},{"_id":"req_6025f2c8a6ca4c9ca32802b034ad605f","authentication":{"token":"{{ token  }}","type":"bearer"},"body":{},"created":1578786516713,"description":"","headers":[],"isPrivate":false,"metaSortKey":-1578756764698.25,"method":"DELETE","modified":1578841822727,"name":"Delete","parameters":[],"parentId":"fld_08cb52c5097640a78c444ca84a2f5637","settingDisableRenderRequestBody":false,"settingEncodeUrl":true,"settingFollowRedirects":"global","settingRebuildPath":true,"settingSendCookies":true,"settingStoreCookies":true,"url":"{{ base_url  }}/appointments/6","_type":"request"},{"_id":"req_4d41f3b0872248a6a6d913f151ac2d3a","authentication":{"token":"{{ token  }}","type":"bearer"},"body":{},"created":1578760457029,"description":"","headers":[],"isPrivate":false,"metaSortKey":-1578755668110.5,"method":"GET","modified":1578786677764,"name":"List","parameters":[{"description":"","id":"pair_95290bd5ca274a80883f879aeb3d17de","name":"page","value":"1"}],"parentId":"fld_08cb52c5097640a78c444ca84a2f5637","settingDisableRenderRequestBody":false,"settingEncodeUrl":true,"settingFollowRedirects":"global","settingRebuildPath":true,"settingSendCookies":true,"settingStoreCookies":true,"url":"{{ base_url  }}/appointments","_type":"request"},{"_id":"req_f4cdc1af1f784ae5bd404269d82c97f2","authentication":{"token":"{{ token  }}","type":"bearer"},"body":{},"created":1578753474935,"description":"","headers":[],"isPrivate":false,"metaSortKey":-1578753474935,"method":"GET","modified":1578753505019,"name":"index","parameters":[],"parentId":"fld_68642606155846248afd7d2da4adf510","settingDisableRenderRequestBody":false,"settingEncodeUrl":true,"settingFollowRedirects":"global","settingRebuildPath":true,"settingSendCookies":true,"settingStoreCookies":true,"url":"{{ base_url  }}/providers","_type":"request"},{"_id":"fld_68642606155846248afd7d2da4adf510","created":1578753457389,"description":"","environment":{},"environmentPropertyOrder":null,"metaSortKey":-1578753457389,"modified":1578753457389,"name":"Providers","parentId":"wrk_e5c94a721cc94e7e8b78ccd22896b9b0","_type":"request_group"},{"_id":"req_9b56274e417943ff9652aa4bfd5df8af","authentication":{"token":"{{ token  }}","type":"bearer"},"body":{"mimeType":"multipart/form-data","params":[{"description":"","fileName":"/home/maikerodrigues/Pictures/124577.jpg","id":"pair_e7f2eaa019a14d428ab0a23bc4a7f8a9","name":"file","type":"file","value":""}]},"created":1578747491825,"description":"","headers":[{"id":"pair_ebd29380e18f427cb76628046e008b8f","name":"Content-Type","value":"multipart/form-data"}],"isPrivate":false,"metaSortKey":-1578747491826,"method":"POST","modified":1578747661634,"name":"Create","parameters":[],"parentId":"fld_2bd121e7e64d4568984eb5ada1be029a","settingDisableRenderRequestBody":false,"settingEncodeUrl":true,"settingFollowRedirects":"global","settingRebuildPath":true,"settingSendCookies":true,"settingStoreCookies":true,"url":"{{ base_url  }}/files","_type":"request"},{"_id":"fld_2bd121e7e64d4568984eb5ada1be029a","created":1578747477743,"description":"","environment":{},"environmentPropertyOrder":null,"metaSortKey":-1578747477743,"modified":1578747477743,"name":"Files","parentId":"wrk_e5c94a721cc94e7e8b78ccd22896b9b0","_type":"request_group"},{"_id":"req_cd4be04febff4fd0a6ea46542ed85c9c","authentication":{},"body":{"mimeType":"application/json","text":"{\n\t\"name\": \"Maike\",\n\t\"email\": \"maikefdn13@gmail.com\",\n\t\"password\": \"maike\"\n}"},"created":1578674919385,"description":"","headers":[{"id":"pair_4a2ed7229cf14a5c9cdfcfde3b258036","name":"Content-Type","value":"application/json"}],"isPrivate":false,"metaSortKey":-1578674919386,"method":"POST","modified":1578703769512,"name":"Create ","parameters":[],"parentId":"fld_cbfe7a77355545c49aed1dc96a367371","settingDisableRenderRequestBody":false,"settingEncodeUrl":true,"settingFollowRedirects":"global","settingRebuildPath":true,"settingSendCookies":true,"settingStoreCookies":true,"url":"{{ base_url  }}/users","_type":"request"},{"_id":"fld_cbfe7a77355545c49aed1dc96a367371","created":1578674855923,"description":"","environment":{},"environmentPropertyOrder":null,"metaSortKey":-1578674855923,"modified":1578674855923,"name":"Users","parentId":"wrk_e5c94a721cc94e7e8b78ccd22896b9b0","_type":"request_group"},{"_id":"req_b5fe6bceeadb4781a553c9aac092ccc7","authentication":{"token":"{{ token  }}","type":"bearer"},"body":{"mimeType":"application/json","text":"{\n\t\"name\": \"Maike Rodrigues 2\",\n\t\"email\": \"maikefdn13@gmail.com\",\n\t\"oldPassword\": \"maike2\",\n\t\"password\": \"maike2\",\n\t\"confirmPassword\": \"maike2\",\n\t\"avatar_id\": \"2\"\n}"},"created":1578685512856,"description":"","headers":[{"id":"pair_4a2ed7229cf14a5c9cdfcfde3b258036","name":"Content-Type","value":"application/json"}],"isPrivate":false,"metaSortKey":-1578630630807.75,"method":"PUT","modified":1578752708060,"name":"Update","parameters":[],"parentId":"fld_cbfe7a77355545c49aed1dc96a367371","settingDisableRenderRequestBody":false,"settingEncodeUrl":true,"settingFollowRedirects":"global","settingRebuildPath":true,"settingSendCookies":true,"settingStoreCookies":true,"url":"{{ base_url  }}/users","_type":"request"},{"_id":"req_48fb8aa5160248dc9c7a72c89aa0b47e","authentication":{"token":"","type":"bearer"},"body":{"mimeType":"application/json","text":"{\n\t\"email\": \"maikefdn13@gmail.com\",\n\t\"password\": \"maike2\"\n}"},"created":1578678612637,"description":"","headers":[{"id":"pair_4a2ed7229cf14a5c9cdfcfde3b258036","name":"Content-Type","value":"application/json"}],"isPrivate":false,"metaSortKey":-1578674919386,"method":"POST","modified":1578786554871,"name":"Create","parameters":[],"parentId":"fld_5ef0f984ec8a440bbcb2e0fdd2530c97","settingDisableRenderRequestBody":false,"settingEncodeUrl":true,"settingFollowRedirects":"global","settingRebuildPath":true,"settingSendCookies":true,"settingStoreCookies":true,"url":"{{ base_url  }}/sessions","_type":"request"},{"_id":"fld_5ef0f984ec8a440bbcb2e0fdd2530c97","created":1578678612631,"description":"","environment":{},"environmentPropertyOrder":null,"metaSortKey":-1578674855873,"modified":1578678612631,"name":"Sessions","parentId":"wrk_e5c94a721cc94e7e8b78ccd22896b9b0","_type":"request_group"},{"_id":"env_c35c37de724bb73b09f09cbab3c0a0c777fb1252","color":null,"created":1578674803614,"data":{"base_url":"http://localhost:3333","token":"eyJhbGciOiJIUzI1NiIsInR5cCI6IkpXVCJ9.eyJpZCI6MTAsImlhdCI6MTU3ODg0OTIyNiwiZXhwIjoxNTc5NDU0MDI2fQ.Nw9eaHF8eQEHfIDPNxBct6uTcFrfMeTkk2JqZioz4OA"},"dataPropertyOrder":{"&":["base_url","token"]},"isPrivate":false,"metaSortKey":1578674803614,"modified":1578849243106,"name":"Base Environment","parentId":"wrk_e5c94a721cc94e7e8b78ccd22896b9b0","_type":"environment"},{"_id":"jar_c35c37de724bb73b09f09cbab3c0a0c777fb1252","cookies":[],"created":1578674803619,"modified":1578674803619,"name":"Default Jar","parentId":"wrk_e5c94a721cc94e7e8b78ccd22896b9b0","_type":"cookie_jar"}]}